[
  {
    "inputs": [
      { "internalType": "address[]", "name": "initialAllowlist", "type": "address[]" },
      { "internalType": "string[]", "name": "names", "type": "string[]" }
    ],
    "stateMutability": "nonpayable",
    "type": "constructor"
  },
  {
    "anonymous": false,
    "inputs": [
      { "indexed": true, "internalType": "uint256", "name": "swapId", "type": "uint256" },
      { "indexed": true, "internalType": "address", "name": "proposer", "type": "address" }
    ],
    "name": "SwapProposed",
    "type": "event"
  },
  {
    "anonymous": false,
    "inputs": [
      { "indexed": true, "internalType": "uint256", "name": "swapId", "type": "uint256" },
      { "indexed": true, "internalType": "address", "name": "accepter", "type": "address" }
    ],
    "name": "SwapAccepted",
    "type": "event"
  },
  {
    "anonymous": false,
    "inputs": [
      { "indexed": true, "internalType": "uint256", "name": "swapId", "type": "uint256" }
    ],
    "name": "SwapCancelled",
    "type": "event"
  },
  {
    "anonymous": false,
    "inputs": [
      { "indexed": true, "internalType": "address", "name": "collection", "type": "address" },
      { "indexed": false, "internalType": "bool", "name": "allowed", "type": "bool" },
      { "indexed": false, "internalType": "string", "name": "name", "type": "string" }
    ],
    "name": "AllowedCollectionUpdated",
    "type": "event"
  },
  {
    "inputs": [
      { "internalType": "address", "name": "collection", "type": "address" },
      { "internalType": "string", "name": "name", "type": "string" }
    ],
    "name": "addAllowedCollection",
    "outputs": [],
    "stateMutability": "nonpayable",
    "type": "function"
  },
  {
    "inputs": [
      { "internalType": "uint256", "name": "swapId", "type": "uint256" }
    ],
    "name": "acceptSwap",
    "outputs": [],
    "stateMutability": "nonReentrant",
    "type": "function"
  },
  {
    "inputs": [
      { "internalType": "uint256", "name": "swapId", "type": "uint256" }
    ],
    "name": "cancelSwap",
    "outputs": [],
    "stateMutability": "nonReentrant",
    "type": "function"
  },
  {
    "inputs": [],
    "name": "getAllowedCollections",
    "outputs": [
      { "internalType": "address[]", "name": "", "type": "address[]" },
      { "internalType": "string[]", "name": "", "type": "string[]" }
    ],
    "stateMutability": "view",
    "type": "function"
  },
  {
    "inputs": [
      { "internalType": "address", "name": "proposerNFT", "type": "address" },
      { "internalType": "uint256", "name": "proposerTokenId", "type": "uint256" },
      { "internalType": "address", "name": "targetNFT", "type": "address" },
      { "internalType": "uint256", "name": "targetTokenId", "type": "uint256" }
    ],
    "name": "proposeSwap",
    "outputs": [
      { "internalType": "uint256", "name": "", "type": "uint256" }
    ],
    "stateMutability": "nonReentrant",
    "type": "function"
  },
  {
    "inputs": [
      { "internalType": "address", "name": "collection", "type": "address" }
    ],
    "name": "removeAllowedCollection",
    "outputs": [],
    "stateMutability": "nonpayable",
    "type": "function"
  },
  {
    "inputs": [{ "internalType": "uint256", "name": "", "type": "uint256" }],
    "name": "swaps",
    "outputs": [
      { "internalType": "address", "name": "proposer", "type": "address" },
      { "internalType": "address", "name": "proposerNFT", "type": "address" },
      { "internalType": "uint256", "name": "proposerTokenId", "type": "uint256" },
      { "internalType": "address", "name": "targetNFT", "type": "address" },
      { "internalType": "uint256", "name": "targetTokenId", "type": "uint256" },
      { "internalType": "bool", "name": "active", "type": "bool" }
    ],
    "stateMutability": "view",
    "type": "function"
  },
  {
    "inputs": [],
    "name": "swapCount",
    "outputs": [
      { "internalType": "uint256", "name": "", "type": "uint256" }
    ],
    "stateMutability": "view",
    "type": "function"
  }
]
